exonware/xnode/__init__.py
exonware_xnode-0.0.1.dist-info/METADATA
exonware_xnode-0.0.1.dist-info/WHEEL
exonware_xnode-0.0.1.dist-info/licenses/LICENSE
exonware_xnode-0.0.1.dist-info/RECORD
